magique/__init__.py
magique/auth.py
magique/base.py
magique/client.py
magique/protocol.py
magique/ser.py
magique/server.py
magique/version.py
magique/worker.py
magique/utils/__init__.py
magique/utils/log.py
magique/utils/network.py
tests/conftest.py
tests/test_connection.py
tests/test_remote.py
magique-0.6.7.dist-info/METADATA
magique-0.6.7.dist-info/WHEEL
magique-0.6.7.dist-info/top_level.txt
magique-0.6.7.dist-info/RECORD
